<?xml version="1.0" encoding="UTF-8" standalone="yes"?>
<ScenarioTemplate>
    <name>Emergency Convoy Defense</name>
    <stratConScenarioType>SPECIAL_RESUPPLY</stratConScenarioType>
    <shortBriefing>Prevent your resupply falling into the hands of the enemy.</shortBriefing>
    <detailedBriefing>Your convoy has been trapped by an enemy force specialized in hunting down fast-moving targets. They are well-equipped for this type of engagement, and their goal is to intercept and capture your supplies. While securing the convoy is important, your primary objective is to eliminate at least 50% of the enemy force to ensure they cannot continue their raids. If they are not routed here, they will be free to attack other convoys, posing a long-term threat to our supply lines.

The enemy is built for speed and pursuit, meaning direct engagements may not always be favorable. Use ambush tactics, force them into unfavorable terrain, and disrupt their ability to maneuver. They rely on overwhelming pursuit capabilities—deny them the chance to use it effectively. If the convoy can be safely extracted, do so, but not at the expense of allowing the enemy to regroup for future strikes.

We will control the battlefield at the conclusion of this engagement, ensuring that any remaining salvage remains in our possession. Turn the hunters into the hunted, cripple their forces, and make certain they never threaten our supply lines again.</detailedBriefing>
    <battlefieldControl>PLAYER</battlefieldControl>
    <isHostileFacility>false</isHostileFacility>
    <isAlliedFacility>false</isAlliedFacility>
    <mapParameters>
        <allowedTerrainTypes />
        <allowRotation>true</allowRotation>
        <baseHeight>50</baseHeight>
        <baseWidth>17</baseWidth>
        <heightScalingIncrement>0</heightScalingIncrement>
        <mapLocation>AllGroundTerrain</mapLocation>
        <useStandardAtBSizing>false</useStandardAtBSizing>
        <widthScalingIncrement>1</widthScalingIncrement>
    </mapParameters>
    <scenarioForces>
        <entry>
            <key>Player</key>
            <value>
                <actualDeploymentZone>-1</actualDeploymentZone>
                <allowAeroBombs>false</allowAeroBombs>
                <allowedUnitType>-2</allowedUnitType>
                <arrivalTurn>0</arrivalTurn>
                <canReinforceLinked>true</canReinforceLinked>
                <contributesToBV>true</contributesToBV>
                <contributesToMapSize>true</contributesToMapSize>
                <contributesToUnitCount>true</contributesToUnitCount>
                <deployOffboard>false</deployOffboard>
                <deploymentZones>
                    <deploymentZone>6</deploymentZone>
                </deploymentZones>
                <destinationZone>2</destinationZone>
                <fixedUnitCount>0</fixedUnitCount>
                <forceAlignment>0</forceAlignment>
                <forceMultiplier>1.0</forceMultiplier>
                <forceName>Player</forceName>
                <generationMethod>0</generationMethod>
                <generationOrder>1</generationOrder>
                <maxWeightClass>4</maxWeightClass>
                <minWeightClass>0</minWeightClass>
                <objectiveLinkedForces />
                <retreatThreshold>0</retreatThreshold>
                <startingAltitude>0</startingAltitude>
                <syncDeploymentType>None</syncDeploymentType>
                <useArtillery>false</useArtillery>
            </value>
        </entry>
        <entry>
            <key>OpFor</key>
            <value>
                <actualDeploymentZone>-1</actualDeploymentZone>
                <allowAeroBombs>false</allowAeroBombs>
                <allowedUnitType>-2</allowedUnitType>
                <arrivalTurn>0</arrivalTurn>
                <canReinforceLinked>false</canReinforceLinked>
                <contributesToBV>false</contributesToBV>
                <contributesToMapSize>true</contributesToMapSize>
                <contributesToUnitCount>false</contributesToUnitCount>
                <deployOffboard>false</deployOffboard>
                <deploymentZones>
                    <deploymentZone>10</deploymentZone>
                </deploymentZones>
                <destinationZone>5</destinationZone>
                <fixedUnitCount>0</fixedUnitCount>
                <forceAlignment>2</forceAlignment>
                <forceMultiplier>1.0</forceMultiplier>
                <forceName>ANTI_AIRCRAFT</forceName>
                <generationMethod>1</generationMethod>
                <generationOrder>5</generationOrder>
                <maxWeightClass>4</maxWeightClass>
                <minWeightClass>2</minWeightClass>
                <objectiveLinkedForces />
                <retreatThreshold>50</retreatThreshold>
                <startingAltitude>0</startingAltitude>
                <syncDeploymentType>None</syncDeploymentType>
                <useArtillery>false</useArtillery>
            </value>
        </entry>
        <entry>
            <key>SecondOpFor</key>
            <value>
                <actualDeploymentZone>-1</actualDeploymentZone>
                <allowAeroBombs>false</allowAeroBombs>
                <allowedUnitType>5</allowedUnitType>
                <arrivalTurn>0</arrivalTurn>
                <canReinforceLinked>false</canReinforceLinked>
                <contributesToBV>false</contributesToBV>
                <contributesToMapSize>true</contributesToMapSize>
                <contributesToUnitCount>false</contributesToUnitCount>
                <deployOffboard>false</deployOffboard>
                <deploymentZones />
                <destinationZone>5</destinationZone>
                <fixedUnitCount>0</fixedUnitCount>
                <forceAlignment>2</forceAlignment>
                <forceMultiplier>1.0</forceMultiplier>
                <forceName>Pursuing OpFor</forceName>
                <generationMethod>1</generationMethod>
                <generationOrder>5</generationOrder>
                <maxWeightClass>3</maxWeightClass>
                <minWeightClass>1</minWeightClass>
                <objectiveLinkedForces />
                <retreatThreshold>50</retreatThreshold>
                <startingAltitude>0</startingAltitude>
                <objectiveLinkedForces>
                    <objectiveLinkedForce>OpFor</objectiveLinkedForce>
                </objectiveLinkedForces>
                <syncDeploymentType>SameEdge</syncDeploymentType>
                <syncedForceName>Player</syncedForceName>
                <useArtillery>false</useArtillery>
            </value>
        </entry>
    </scenarioForces>
    <scenarioObjectives>
        <scenarioObjective>
            <associatedForceNames>
                <associatedForceName>OpFor</associatedForceName>
            </associatedForceNames>
            <associatedUnitIDs />
            <successEffects>
                <successEffect>
                    <effectType>ScenarioVictory</effectType>
                    <effectScaling>Fixed</effectScaling>
                    <howMuch>1</howMuch>
                </successEffect>
            </successEffects>
            <failureEffects>
                <failureEffect>
                    <effectType>ScenarioDefeat</effectType>
                    <effectScaling>Fixed</effectScaling>
                    <howMuch>1</howMuch>
                </failureEffect>
            </failureEffects>
            <additionalDetails />
            <description>Destroy or rout 50% of the following forces. +1 SVP if succeeded, -1 SVP if failed. Failure also incurs a -1 CVP penalty (StratCon Only).</description>
            <destinationEdge>NONE</destinationEdge>
            <objectiveCriterion>ForceWithdraw</objectiveCriterion>
            <percentage>50</percentage>
            <timeLimit>0</timeLimit>
            <timeLimitAtMost>true</timeLimitAtMost>
            <timeLimitType>None</timeLimitType>
        </scenarioObjective>
        <scenarioObjective>
            <associatedForceNames>
                <associatedForceName>Player</associatedForceName>
            </associatedForceNames>
            <associatedUnitIDs />
            <additionalDetails>
                <additionalDetail>Crippled units do not count towards this objective.</additionalDetail>
            </additionalDetails>
            <description>Reach the destination edge with 50% of the following forces. This objective does not award SVP.</description>
            <destinationEdge>NORTH</destinationEdge>
            <objectiveCriterion>ReachMapEdge</objectiveCriterion>
            <percentage>50</percentage>
            <timeLimit>0</timeLimit>
            <timeLimitAtMost>true</timeLimitAtMost>
            <timeLimitType>None</timeLimitType>
        </scenarioObjective>
    </scenarioObjectives>
</ScenarioTemplate>
